[
	{
		"__TYPE__": "SharedSliceContent",
		"variation": "default",
		"primary": {
			"heading": {
				"__TYPE__": "StructuredTextContent",
				"value": [
					{
						"type": "paragraph",
						"content": {
							"text": "Duis eiusmod cillum elit nulla duis cillum ipsum velit non quis sint esse nostrud. Id qui duis sint mollit minim."
						}
					}
				]
			},
			"image": {
				"origin": {
					"id": "main",
					"url": "https://images.unsplash.com/photo-1471897488648-5eae4ac6686b",
					"width": 3560,
					"height": 5340
				},
				"url": "https://images.unsplash.com/photo-1471897488648-5eae4ac6686b",
				"width": 3560,
				"height": 5340,
				"edit": {
					"zoom": 1,
					"crop": {
						"x": 0,
						"y": 0
					},
					"background": "transparent"
				},
				"credits": null,
				"alt": null,
				"__TYPE__": "ImageContent",
				"thumbnails": {}
			},
			"icon": {
				"__TYPE__": "FieldContent",
				"value": "gear",
				"type": "Select"
			},
			"subheading": {
				"__TYPE__": "StructuredTextContent",
				"value": [
					{
						"type": "heading3",
						"content": {
							"text": "Expression"
						}
					}
				]
			},
			"body": {
				"__TYPE__": "StructuredTextContent",
				"value": [
					{
						"type": "paragraph",
						"content": {
							"text": "Ipsum cillum consequat sunt ea qui."
						}
					}
				]
			},
			"button_text": {
				"__TYPE__": "FieldContent",
				"value": "protection",
				"type": "Text"
			},
			"button_link": {
				"__TYPE__": "LinkContent",
				"value": {
					"__TYPE__": "ExternalLink",
					"url": "http://twitter.com",
					"text": "examine"
				}
			},
			"techstacks": {
				"__TYPE__": "StructuredTextContent",
				"value": [
					{
						"type": "paragraph",
						"content": {
							"text": "Laboris Lorem cupidatat velit proident id est esse ea. Ad reprehenderit cillum eiusmod."
						}
					}
				]
			}
		},
		"items": []
	},
	{
		"__TYPE__": "SharedSliceContent",
		"variation": "reverse",
		"primary": {
			"heading": {
				"__TYPE__": "StructuredTextContent",
				"value": [
					{
						"type": "heading2",
						"content": {
							"text": "Different"
						}
					}
				]
			},
			"image": {
				"origin": {
					"id": "main",
					"url": "https://images.unsplash.com/photo-1551739440-5dd934d3a94a",
					"width": 3456,
					"height": 4320
				},
				"url": "https://images.unsplash.com/photo-1551739440-5dd934d3a94a",
				"width": 3456,
				"height": 4320,
				"edit": {
					"zoom": 1,
					"crop": {
						"x": 0,
						"y": 0
					},
					"background": "transparent"
				},
				"credits": null,
				"alt": null,
				"__TYPE__": "ImageContent",
				"thumbnails": {}
			},
			"icon": {
				"__TYPE__": "FieldContent",
				"value": "cycle",
				"type": "Select"
			},
			"subheading": {
				"__TYPE__": "StructuredTextContent",
				"value": [
					{
						"type": "heading3",
						"content": {
							"text": "Morning"
						}
					}
				]
			},
			"body": {
				"__TYPE__": "StructuredTextContent",
				"value": [
					{
						"type": "paragraph",
						"content": {
							"text": "Officia laborum sit sunt pariatur."
						}
					}
				]
			},
			"button_text": {
				"__TYPE__": "FieldContent",
				"value": "bow",
				"type": "Text"
			},
			"button_link": {
				"__TYPE__": "LinkContent",
				"value": {
					"__TYPE__": "ExternalLink",
					"url": "https://slicemachine.dev",
					"text": "fireplace"
				}
			}
		},
		"items": [
			{
				"__TYPE__": "GroupItemContent",
				"value": []
			}
		]
	}
]